pysuez/__init__.py
pysuez/__main__.py
pysuez/client.py
pysuez_fork-0.2.1.dist-info/LICENSE
pysuez_fork-0.2.1.dist-info/METADATA
pysuez_fork-0.2.1.dist-info/WHEEL
pysuez_fork-0.2.1.dist-info/entry_points.txt
pysuez_fork-0.2.1.dist-info/top_level.txt
pysuez_fork-0.2.1.dist-info/RECORD
